tdbug/__init__.py
tdbug/main.py
tdbug-1.0.8.dist-info/METADATA
tdbug-1.0.8.dist-info/WHEEL
tdbug-1.0.8.dist-info/licenses/LICENSE
tdbug-1.0.8.dist-info/RECORD
