Metadata-Version: 2.1
Name: tdbug
Version: 1.0.8
Summary: tdbug is a command-line application that uses the OpenAI API to diagnose bugs when programming.
Project-URL: Homepage, https://github.com/damonpickett/tdbug
Project-URL: Bug Tracker, https://github.com/damonpickett/tdbug/issues
Author-email: Damon Pickett <damon.pickett@gmail.com>
License-File: LICENSE
Classifier: License :: OSI Approved :: MIT License
Classifier: Operating System :: OS Independent
Classifier: Programming Language :: Python :: 3
Requires-Python: >=3.7
